{"trial_id": "737824beccfb4a84057934ab4dc0f82e", "hyperparameters": {"space": [{"class_name": "Choice", "config": {"name": "units", "default": 128, "conditions": [], "values": [128, 256, 512], "ordered": true}}, {"class_name": "Choice", "config": {"name": "activation", "default": "relu", "conditions": [], "values": ["relu"], "ordered": false}}, {"class_name": "Choice", "config": {"name": "noise", "default": 0.2, "conditions": [], "values": [0.2, 0.3, 0.4], "ordered": true}}, {"class_name": "Choice", "config": {"name": "units2", "default": 128, "conditions": [], "values": [128, 256, 512], "ordered": true}}, {"class_name": "Choice", "config": {"name": "activation2", "default": "relu", "conditions": [], "values": ["relu"], "ordered": false}}, {"class_name": "Choice", "config": {"name": "noise2", "default": 0.2, "conditions": [], "values": [0.2, 0.3, 0.4], "ordered": true}}, {"class_name": "Choice", "config": {"name": "classification", "default": "softmax", "conditions": [], "values": ["softmax"], "ordered": false}}, {"class_name": "Choice", "config": {"name": "loss", "default": "categorical_crossentropy", "conditions": [], "values": ["categorical_crossentropy"], "ordered": false}}, {"class_name": "Choice", "config": {"name": "optimizers", "default": "adam", "conditions": [], "values": ["adam"], "ordered": false}}], "values": {"units": 512, "activation": "relu", "noise": 0.3, "units2": 128, "activation2": "relu", "noise2": 0.4, "classification": "softmax", "loss": "categorical_crossentropy", "optimizers": "adam"}}, "metrics": {"metrics": {"loss": {"direction": "min", "observations": [{"value": [1.0547515749931335], "step": 0}]}, "mae": {"direction": "min", "observations": [{"value": [0.14358313381671906], "step": 0}]}, "acc": {"direction": "max", "observations": [{"value": [0.9616991579532623], "step": 0}]}, "val_loss": {"direction": "min", "observations": [{"value": [0.5167368352413177], "step": 0}]}, "val_mae": {"direction": "min", "observations": [{"value": [0.08367696776986122], "step": 0}]}, "val_acc": {"direction": "max", "observations": [{"value": [0.9361111223697662], "step": 0}]}}}, "score": 0.9361111223697662, "best_step": 0, "status": "COMPLETED"}